{
  "version": "Integrated equipment update",
  "updated": "2026-07-15",
  "counts": {
    "physical": 18,
    "magic": 18,
    "defense": 15,
    "support": 13
  },
  "items": [
    {
      "id": "boots-of-speed",
      "name": "速度之靴",
      "category": "鞋子",
      "tier": 1,
      "order": 1,
      "icon": "../assets/images/items/shoes/boots-of-speed.png",
      "stats": [
        "+25 跑速"
      ],
      "passives": [],
      "buildFrom": [],
      "upgrades": [
        "gluttonous-greaves",
        "berserkers-greaves",
        "mercurys-treads",
        "plated-steelcaps",
        "ionian-boots",
        "mana-boots",
        "burst-boots"
      ],
      "stage": "鞋子",
      "categories": [
        "鞋子"
      ]
    },
    {
      "id": "gluttonous-greaves",
      "name": "貪婪護脛",
      "category": "鞋子",
      "tier": 2,
      "order": 2,
      "icon": "../assets/images/items/shoes/gluttonous-greaves.png",
      "stats": [
        "+45 跑速",
        "獲得 12 物攻或 20 魔攻（適性）",
        "+5% 全能吸血"
      ],
      "passives": [
        "鮮血轉換：參與擊殺英雄會額外獲得0.5%全能吸血效果，最高5%。"
      ],
      "buildFrom": [
        "boots-of-speed"
      ],
      "upgrades": [
        "immortal-boots"
      ],
      "stage": "鞋子",
      "categories": [
        "鞋子"
      ]
    },
    {
      "id": "berserkers-greaves",
      "name": "狂戰士護脛",
      "category": "鞋子",
      "tier": 2,
      "order": 3,
      "icon": "../assets/images/items/shoes/berserkers-greaves.png",
      "stats": [
        "+30% 攻擊速度",
        "+45 跑速"
      ],
      "passives": [
        "護佑之鋒：普攻命中時，回復10生命。"
      ],
      "buildFrom": [
        "boots-of-speed",
        "dagger"
      ],
      "upgrades": [
        "gunsteel-greaves"
      ],
      "stage": "鞋子",
      "categories": [
        "鞋子"
      ]
    },
    {
      "id": "mercurys-treads",
      "name": "水星之靴",
      "category": "鞋子",
      "tier": 2,
      "order": 4,
      "icon": "../assets/images/items/shoes/mercurys-treads.png",
      "stats": [
        "+150 最大生命",
        "+25 魔法防禦",
        "+15% 韌性",
        "+45 跑速"
      ],
      "passives": [],
      "buildFrom": [
        "boots-of-speed",
        "ruby-crystal"
      ],
      "upgrades": [
        "chain-army-boots"
      ],
      "stage": "鞋子",
      "categories": [
        "鞋子"
      ]
    },
    {
      "id": "plated-steelcaps",
      "name": "鍍板鋼蓋",
      "category": "鞋子",
      "tier": 2,
      "order": 5,
      "icon": "../assets/images/items/shoes/plated-steelcaps.png",
      "stats": [
        "+150 最大生命",
        "+25 物理防禦",
        "+45 跑速"
      ],
      "passives": [
        "格擋：所受的英雄普攻傷害降低6%。"
      ],
      "buildFrom": [
        "boots-of-speed",
        "ruby-crystal"
      ],
      "upgrades": [
        "armored-warboots"
      ],
      "stage": "鞋子",
      "categories": [
        "鞋子"
      ]
    },
    {
      "id": "ionian-boots",
      "name": "愛歐尼亞之靴",
      "category": "鞋子",
      "tier": 2,
      "order": 6,
      "icon": "../assets/images/items/shoes/ionian-boots.png",
      "stats": [
        "+50% 魔力回復",
        "+15 技能加速",
        "+45 跑速"
      ],
      "passives": [
        "召喚加速：減少15%召喚師技能冷卻時間。"
      ],
      "buildFrom": [
        "boots-of-speed",
        "mana-ring"
      ],
      "upgrades": [
        "blood-mage-boots"
      ],
      "stage": "鞋子",
      "categories": [
        "鞋子"
      ]
    },
    {
      "id": "mana-boots",
      "name": "魔力之靴",
      "category": "鞋子",
      "tier": 2,
      "order": 7,
      "icon": "../assets/images/items/shoes/mana-boots.png",
      "stats": [
        "+25 魔法攻擊",
        "+8 魔法穿透",
        "+75% 魔力回復",
        "+45 跑速"
      ],
      "passives": [
        "維持均衡：沒有魔力的英雄則增加50%基礎生命回復。",
        "大惡霸：普攻和主動技能對士兵造成18額外真實傷害。"
      ],
      "buildFrom": [
        "boots-of-speed",
        "amp-tome"
      ],
      "upgrades": [
        "sorcerers-shoes"
      ],
      "stage": "鞋子",
      "categories": [
        "鞋子"
      ]
    },
    {
      "id": "burst-boots",
      "name": "爆發之靴",
      "category": "鞋子",
      "tier": 2,
      "order": 8,
      "icon": "../assets/images/items/shoes/burst-boots.png",
      "stats": [
        "+15 物理攻擊",
        "+10 物理穿透",
        "+45 跑速"
      ],
      "passives": [],
      "buildFrom": [
        "boots-of-speed",
        "long-sword"
      ],
      "upgrades": [
        "armorbreaker-boots"
      ],
      "stage": "鞋子",
      "categories": [
        "鞋子"
      ]
    },
    {
      "id": "immortal-boots",
      "name": "不朽之靴",
      "category": "鞋子",
      "tier": 3,
      "order": 9,
      "icon": "../assets/images/items/shoes/immortal-boots.png",
      "stats": [
        "+45 跑速",
        "獲得 12 物攻或 20 魔攻（適性）",
        "+5% 全能吸血"
      ],
      "passives": [
        "鮮血轉換：參與擊殺英雄會額外獲得0.5%全能吸血，最高5%。",
        "永恆不滅：生命高於50%時造成5%額外傷害；生命低於50%時，治療與護盾量增加12%。"
      ],
      "buildFrom": [
        "gluttonous-greaves"
      ],
      "upgrades": [],
      "stage": "鞋子",
      "categories": [
        "鞋子"
      ]
    },
    {
      "id": "gunsteel-greaves",
      "name": "槍鋼護脛",
      "category": "鞋子",
      "tier": 3,
      "order": 10,
      "icon": "../assets/images/items/shoes/gunsteel-greaves.png",
      "stats": [
        "+50% 攻擊速度",
        "+5% 物理吸血",
        "+45 跑速"
      ],
      "passives": [
        "諾克薩斯步法：普攻敵方英雄可增加跑速（近戰15%、遠程12%），2秒內逐漸衰減。",
        "護佑之鋒：普攻命中時，回復12生命。"
      ],
      "buildFrom": [
        "berserkers-greaves"
      ],
      "upgrades": [],
      "stage": "鞋子",
      "categories": [
        "鞋子"
      ]
    },
    {
      "id": "chain-army-boots",
      "name": "鎖鏈軍靴",
      "category": "鞋子",
      "tier": 3,
      "order": 11,
      "icon": "../assets/images/items/shoes/chain-army-boots.png",
      "stats": [
        "+150 最大生命",
        "+35 魔法防禦",
        "+30% 韌性",
        "+45 跑速"
      ],
      "passives": [
        "諾克薩斯意志力：受到來自英雄的魔法傷害時，獲得可吸收20–140＋5%最大生命傷害的魔法護盾，持續5秒（冷卻12秒）。"
      ],
      "buildFrom": [
        "mercurys-treads"
      ],
      "upgrades": [],
      "stage": "鞋子",
      "categories": [
        "鞋子"
      ]
    },
    {
      "id": "armored-warboots",
      "name": "裝甲戰靴",
      "category": "鞋子",
      "tier": 3,
      "order": 12,
      "icon": "../assets/images/items/shoes/armored-warboots.png",
      "stats": [
        "+150 最大生命",
        "+35 物理防禦",
        "+45 跑速"
      ],
      "passives": [
        "格擋：所受的英雄普攻傷害降低10%。",
        "諾克薩斯耐力：受到來自英雄的物理傷害後，獲得可吸收20–140＋5%最大生命傷害的物理護盾，持續5秒（冷卻12秒）。"
      ],
      "buildFrom": [
        "plated-steelcaps"
      ],
      "upgrades": [],
      "stage": "鞋子",
      "categories": [
        "鞋子"
      ]
    },
    {
      "id": "blood-mage-boots",
      "name": "血色法靴",
      "category": "鞋子",
      "tier": 3,
      "order": 13,
      "icon": "../assets/images/items/shoes/blood-mage-boots.png",
      "stats": [
        "+75% 魔力回復",
        "+25 技能加速",
        "+45 跑速"
      ],
      "passives": [
        "召喚加速：減少20%召喚師技能冷卻時間。",
        "諾克薩斯加速：治療、賦予護盾、施放技能，或技能對敵方造成傷害時獲得跑速（近戰10%、遠程8%），持續4秒；每項技能每4秒只觸發一次。"
      ],
      "buildFrom": [
        "ionian-boots"
      ],
      "upgrades": [],
      "stage": "鞋子",
      "categories": [
        "鞋子"
      ]
    },
    {
      "id": "sorcerers-shoes",
      "name": "魔法使之鞋",
      "category": "鞋子",
      "tier": 3,
      "order": 14,
      "icon": "../assets/images/items/shoes/sorcerers-shoes.png",
      "stats": [
        "+40 魔法攻擊",
        "+18 魔法穿透",
        "+8% 魔法穿透",
        "+100% 魔力回復",
        "+45 跑速"
      ],
      "passives": [
        "維持均衡：沒有魔力的英雄則增加50%基礎生命回復。",
        "大惡霸：普攻和主動技能對士兵造成22額外真實傷害。"
      ],
      "buildFrom": [
        "mana-boots"
      ],
      "upgrades": [],
      "stage": "鞋子",
      "categories": [
        "鞋子"
      ]
    },
    {
      "id": "armorbreaker-boots",
      "name": "碎甲者之靴",
      "category": "鞋子",
      "tier": 3,
      "order": 15,
      "icon": "../assets/images/items/shoes/armorbreaker-boots.png",
      "stats": [
        "+25 物理攻擊",
        "+12 物理穿透",
        "+6% 物理穿透",
        "+45 跑速"
      ],
      "passives": [
        "雲行者：獲得20脫離戰鬥跑速。"
      ],
      "buildFrom": [
        "burst-boots"
      ],
      "upgrades": [],
      "stage": "鞋子",
      "categories": [
        "鞋子"
      ]
    },
    {
      "id": "intermediate-01",
      "name": "閃耀劍",
      "category": "物理",
      "categories": [
        "物理",
        "魔法",
        "防禦"
      ],
      "stage": "中階",
      "tier": "中階",
      "order": 100,
      "icon": "../assets/images/items/閃耀劍.webp",
      "price": 800,
      "stats": [
        "+10 技能加速"
      ],
      "passives": [
        "施放技能後，下一次普攻造成額外物理傷害；攻擊建築物時傷害降低。"
      ],
      "buildFrom": [],
      "upgrades": []
    },
    {
      "id": "intermediate-02",
      "name": "吸血鬼權杖",
      "category": "物理",
      "categories": [
        "物理"
      ],
      "stage": "中階",
      "tier": "中階",
      "order": 101,
      "icon": "../assets/images/items/吸血鬼權杖.webp",
      "price": 1200,
      "stats": [
        "+20 物理攻擊",
        "+8% 物理吸血"
      ],
      "passives": [],
      "buildFrom": [],
      "upgrades": []
    },
    {
      "id": "intermediate-03",
      "name": "狂熱雙刀",
      "category": "物理",
      "categories": [
        "物理"
      ],
      "stage": "中階",
      "tier": "中階",
      "order": 102,
      "icon": "../assets/images/items/狂熱雙刀.webp",
      "price": 1400,
      "stats": [
        "+15% 暴擊率",
        "+15% 攻擊速度",
        "+5% 跑速"
      ],
      "passives": [],
      "buildFrom": [],
      "upgrades": []
    },
    {
      "id": "intermediate-04",
      "name": "科奇碎片",
      "category": "物理",
      "categories": [
        "物理"
      ],
      "stage": "中階",
      "tier": "中階",
      "order": 103,
      "icon": "../assets/images/items/科奇碎片.webp",
      "price": 900,
      "stats": [
        "+15 物理攻擊"
      ],
      "passives": [
        "充能普攻造成額外魔法傷害；移動與攻擊可產生充能。"
      ],
      "buildFrom": [],
      "upgrades": []
    },
    {
      "id": "intermediate-05",
      "name": "正午箭筒",
      "category": "物理",
      "categories": [
        "物理"
      ],
      "stage": "中階",
      "tier": "中階",
      "order": 104,
      "icon": "../assets/images/items/正午箭筒.webp",
      "price": 1350,
      "stats": [
        "+25 物理攻擊",
        "+15% 攻擊速度"
      ],
      "passives": [],
      "buildFrom": [],
      "upgrades": []
    },
    {
      "id": "intermediate-06",
      "name": "納什之爪",
      "category": "物理",
      "categories": [
        "物理",
        "魔法"
      ],
      "stage": "中階",
      "tier": "中階",
      "order": 105,
      "icon": "../assets/images/items/納什之爪.webp",
      "price": 800,
      "stats": [
        "+15 物理攻擊或 +30 魔法攻擊（適性）"
      ],
      "passives": [],
      "buildFrom": [],
      "upgrades": []
    },
    {
      "id": "intermediate-07",
      "name": "殘暴之力",
      "category": "物理",
      "categories": [
        "物理"
      ],
      "stage": "中階",
      "tier": "中階",
      "order": 106,
      "icon": "../assets/images/items/殘暴之力.webp",
      "price": 1000,
      "stats": [
        "+20 物理攻擊",
        "+8 物理穿透"
      ],
      "passives": [],
      "buildFrom": [],
      "upgrades": []
    },
    {
      "id": "intermediate-08",
      "name": "反曲弓",
      "category": "物理",
      "categories": [
        "物理"
      ],
      "stage": "中階",
      "tier": "中階",
      "order": 107,
      "icon": "../assets/images/items/反曲弓.webp",
      "price": 1400,
      "stats": [
        "+30% 攻擊速度"
      ],
      "passives": [
        "普攻命中目標時造成額外物理傷害。"
      ],
      "buildFrom": [],
      "upgrades": []
    },
    {
      "id": "intermediate-09",
      "name": "暴風之劍",
      "category": "物理",
      "categories": [
        "物理"
      ],
      "stage": "中階",
      "tier": "中階",
      "order": 108,
      "icon": "../assets/images/items/暴風之劍.webp",
      "price": 1500,
      "stats": [
        "+40 物理攻擊"
      ],
      "passives": [],
      "buildFrom": [],
      "upgrades": []
    },
    {
      "id": "intermediate-10",
      "name": "靈巧披風",
      "category": "物理",
      "categories": [
        "物理"
      ],
      "stage": "中階",
      "tier": "中階",
      "order": 109,
      "icon": "../assets/images/items/靈巧披風.webp",
      "price": 1000,
      "stats": [
        "+20% 暴擊率"
      ],
      "passives": [],
      "buildFrom": [],
      "upgrades": []
    },
    {
      "id": "intermediate-11",
      "name": "最後耳語",
      "category": "物理",
      "categories": [
        "物理"
      ],
      "stage": "中階",
      "tier": "中階",
      "order": 110,
      "icon": "../assets/images/items/最後耳語.webp",
      "price": 800,
      "stats": [
        "+12% 物理穿透"
      ],
      "passives": [],
      "buildFrom": [],
      "upgrades": []
    },
    {
      "id": "intermediate-12",
      "name": "死刑宣告",
      "category": "物理",
      "categories": [
        "物理"
      ],
      "stage": "中階",
      "tier": "中階",
      "order": 111,
      "icon": "../assets/images/items/死刑宣告.webp",
      "price": 800,
      "stats": [
        "+15 物理攻擊"
      ],
      "passives": [
        "對敵方英雄造成物理傷害時附加 40% 重創，持續 3 秒。"
      ],
      "buildFrom": [],
      "upgrades": []
    },
    {
      "id": "intermediate-13",
      "name": "淨蝕之槌",
      "category": "物理",
      "categories": [
        "物理"
      ],
      "stage": "中階",
      "tier": "中階",
      "order": 112,
      "icon": "../assets/images/items/淨蝕之槌.webp",
      "price": 1000,
      "stats": [
        "+150 最大生命",
        "+15 物理攻擊"
      ],
      "passives": [
        "普攻增加跑速；擊殺時增加更多跑速，遠攻英雄效果減半。"
      ],
      "buildFrom": [],
      "upgrades": []
    },
    {
      "id": "intermediate-14",
      "name": "刺針劍",
      "category": "物理",
      "categories": [
        "物理",
        "魔法"
      ],
      "stage": "中階",
      "tier": "中階",
      "order": 113,
      "icon": "../assets/images/items/刺針劍.webp",
      "price": 1200,
      "stats": [
        "+30% 攻擊速度",
        "+10 技能加速"
      ],
      "passives": [],
      "buildFrom": [],
      "upgrades": []
    },
    {
      "id": "intermediate-15",
      "name": "吸魔劍",
      "category": "物理",
      "categories": [
        "物理"
      ],
      "stage": "中階",
      "tier": "中階",
      "order": 114,
      "icon": "../assets/images/items/吸魔劍.webp",
      "price": 1200,
      "stats": [
        "+20 物理攻擊",
        "+20 魔法防禦"
      ],
      "passives": [],
      "buildFrom": [],
      "upgrades": []
    },
    {
      "id": "intermediate-16",
      "name": "考菲爾德的戰槌",
      "category": "物理",
      "categories": [
        "物理"
      ],
      "stage": "中階",
      "tier": "中階",
      "order": 115,
      "icon": "../assets/images/items/考菲爾德的戰槌.webp",
      "price": 1200,
      "stats": [
        "+25 物理攻擊",
        "+10 技能加速"
      ],
      "passives": [],
      "buildFrom": [],
      "upgrades": []
    },
    {
      "id": "intermediate-17",
      "name": "燃燒寶石",
      "category": "物理",
      "categories": [
        "物理",
        "魔法",
        "防禦",
        "輔助"
      ],
      "stage": "中階",
      "tier": "中階",
      "order": 116,
      "icon": "../assets/images/items/燃燒寶石.webp",
      "price": 1000,
      "stats": [
        "+175 最大生命",
        "+10 技能加速"
      ],
      "passives": [],
      "buildFrom": [],
      "upgrades": []
    },
    {
      "id": "intermediate-18",
      "name": "約瑞姆之拳",
      "category": "物理",
      "categories": [
        "物理",
        "防禦"
      ],
      "stage": "中階",
      "tier": "中階",
      "order": 117,
      "icon": "../assets/images/items/約瑞姆之拳.webp",
      "price": 1200,
      "stats": [
        "+200 最大生命",
        "+15 物理攻擊"
      ],
      "passives": [],
      "buildFrom": [],
      "upgrades": []
    },
    {
      "id": "intermediate-19",
      "name": "蒼翠屏障",
      "category": "魔法",
      "categories": [
        "魔法",
        "防禦",
        "輔助"
      ],
      "stage": "中階",
      "tier": "中階",
      "order": 118,
      "icon": "../assets/images/items/蒼翠屏障.webp",
      "price": 1600,
      "stats": [
        "+40 魔法攻擊",
        "+25 魔法防禦"
      ],
      "passives": [
        "獲得一道法術護盾，可阻擋下一次敵方技能。"
      ],
      "buildFrom": [],
      "upgrades": []
    },
    {
      "id": "intermediate-20",
      "name": "命定灰燼",
      "category": "魔法",
      "categories": [
        "魔法",
        "輔助"
      ],
      "stage": "中階",
      "tier": "中階",
      "order": 119,
      "icon": "../assets/images/items/命定灰燼.webp",
      "price": 900,
      "stats": [
        "+40 魔法攻擊"
      ],
      "passives": [
        "傷害性技能在 3 秒內造成額外魔法傷害；對野怪造成額外傷害。"
      ],
      "buildFrom": [],
      "upgrades": []
    },
    {
      "id": "intermediate-21",
      "name": "靈魂竊取者",
      "category": "魔法",
      "categories": [
        "魔法"
      ],
      "stage": "中階",
      "tier": "中階",
      "order": 120,
      "icon": "../assets/images/items/靈魂竊取者.webp",
      "price": 1800,
      "stats": [
        "+70 最大生命",
        "+25 魔法攻擊"
      ],
      "passives": [
        "擊殺或助攻取得榮耀層數；層數提供魔法攻擊，死亡會失去部分層數。"
      ],
      "buildFrom": [],
      "upgrades": []
    },
    {
      "id": "intermediate-22",
      "name": "蒼穹神火",
      "category": "魔法",
      "categories": [
        "魔法"
      ],
      "stage": "中階",
      "tier": "中階",
      "order": 121,
      "icon": "../assets/images/items/蒼穹神火.webp",
      "price": 950,
      "stats": [
        "+35 魔法攻擊",
        "+5% 跑速"
      ],
      "passives": [],
      "buildFrom": [],
      "upgrades": []
    },
    {
      "id": "intermediate-23",
      "name": "失落之章",
      "category": "魔法",
      "categories": [
        "魔法",
        "輔助"
      ],
      "stage": "中階",
      "tier": "中階",
      "order": 122,
      "icon": "../assets/images/items/失落之章.webp",
      "price": 1200,
      "stats": [
        "+35 魔法攻擊",
        "+200 最大魔力",
        "+10 技能加速"
      ],
      "passives": [
        "升級時於 3 秒內回復 20% 最大魔力。"
      ],
      "buildFrom": [],
      "upgrades": []
    },
    {
      "id": "intermediate-24",
      "name": "惡魔法典",
      "category": "魔法",
      "categories": [
        "魔法",
        "輔助"
      ],
      "stage": "中階",
      "tier": "中階",
      "order": 123,
      "icon": "../assets/images/items/惡魔法典.webp",
      "price": 900,
      "stats": [
        "+25 魔法攻擊",
        "+10 技能加速"
      ],
      "passives": [],
      "buildFrom": [],
      "upgrades": []
    },
    {
      "id": "intermediate-25",
      "name": "爆裂魔杖",
      "category": "魔法",
      "categories": [
        "魔法"
      ],
      "stage": "中階",
      "tier": "中階",
      "order": 124,
      "icon": "../assets/images/items/爆裂魔杖.webp",
      "price": 800,
      "stats": [
        "+40 魔法攻擊"
      ],
      "passives": [],
      "buildFrom": [],
      "upgrades": []
    },
    {
      "id": "intermediate-26",
      "name": "巨型魔棒",
      "category": "魔法",
      "categories": [
        "魔法"
      ],
      "stage": "中階",
      "tier": "中階",
      "order": 125,
      "icon": "../assets/images/items/巨型魔棒.webp",
      "price": 1400,
      "stats": [
        "+65 魔法攻擊"
      ],
      "passives": [],
      "buildFrom": [],
      "upgrades": []
    },
    {
      "id": "intermediate-27",
      "name": "幽魂面具",
      "category": "魔法",
      "categories": [
        "魔法"
      ],
      "stage": "中階",
      "tier": "中階",
      "order": 126,
      "icon": "../assets/images/items/幽魂面具.webp",
      "price": 1300,
      "stats": [
        "+200 最大生命",
        "+30 魔法攻擊"
      ],
      "passives": [
        "與敵方英雄戰鬥時逐步增加額外傷害。"
      ],
      "buildFrom": [],
      "upgrades": []
    },
    {
      "id": "intermediate-28",
      "name": "催化魔方",
      "category": "魔法",
      "categories": [
        "魔法",
        "防禦",
        "輔助"
      ],
      "stage": "中階",
      "tier": "中階",
      "order": 127,
      "icon": "../assets/images/items/催化魔方.webp",
      "price": 1100,
      "stats": [
        "+200 最大生命",
        "+300 最大魔力"
      ],
      "passives": [
        "受到英雄傷害後回復魔力；消耗魔力後回復生命。"
      ],
      "buildFrom": [],
      "upgrades": []
    },
    {
      "id": "intermediate-29",
      "name": "遺忘寶珠",
      "category": "魔法",
      "categories": [
        "魔法"
      ],
      "stage": "中階",
      "tier": "中階",
      "order": 128,
      "icon": "../assets/images/items/遺忘寶珠.webp",
      "price": 900,
      "stats": [
        "+35 魔法攻擊"
      ],
      "passives": [
        "對敵方英雄造成魔法傷害時附加 40% 重創，持續 3 秒。"
      ],
      "buildFrom": [],
      "upgrades": []
    },
    {
      "id": "intermediate-30",
      "name": "虛空紫晶",
      "category": "魔法",
      "categories": [
        "魔法"
      ],
      "stage": "中階",
      "tier": "中階",
      "order": 129,
      "icon": "../assets/images/items/虛空紫晶.webp",
      "price": 1000,
      "stats": [
        "+20 魔法攻擊",
        "+10% 魔法穿透"
      ],
      "passives": [
        "激鬥峽谷專用新版圖示。"
      ],
      "buildFrom": [],
      "upgrades": []
    },
    {
      "id": "intermediate-31",
      "name": "海克斯科技發電機",
      "category": "魔法",
      "categories": [
        "魔法"
      ],
      "stage": "中階",
      "tier": "中階",
      "order": 130,
      "icon": "../assets/images/items/海克斯科技發電機.webp",
      "price": 1100,
      "stats": [
        "+45 魔法攻擊"
      ],
      "passives": [
        "傷害性技能強化普攻，對英雄造成額外魔法傷害。"
      ],
      "buildFrom": [],
      "upgrades": []
    },
    {
      "id": "intermediate-32",
      "name": "禁忌之像",
      "category": "魔法",
      "categories": [
        "魔法",
        "輔助"
      ],
      "stage": "中階",
      "tier": "中階",
      "order": 131,
      "icon": "../assets/images/items/禁忌之像.webp",
      "price": 900,
      "stats": [
        "+100 最大生命",
        "+25% 魔力回復",
        "+5 技能加速",
        "+4% 治療和護盾量"
      ],
      "passives": [],
      "buildFrom": [],
      "upgrades": []
    },
    {
      "id": "intermediate-33",
      "name": "巴米灰燼",
      "category": "防禦",
      "categories": [
        "防禦"
      ],
      "stage": "中階",
      "tier": "中階",
      "order": 132,
      "icon": "../assets/images/items/巴米灰燼.webp",
      "price": 1300,
      "stats": [
        "+250 最大生命"
      ],
      "passives": [
        "每秒對附近敵人造成魔法傷害；對士兵與野怪傷害提高。"
      ],
      "buildFrom": [],
      "upgrades": []
    },
    {
      "id": "intermediate-34",
      "name": "亡靈斗篷",
      "category": "防禦",
      "categories": [
        "防禦",
        "輔助"
      ],
      "stage": "中階",
      "tier": "中階",
      "order": 133,
      "icon": "../assets/images/items/亡靈斗篷.webp",
      "price": 1100,
      "stats": [
        "+175 最大生命",
        "+20 魔法防禦"
      ],
      "passives": [
        "受到敵方英雄傷害後，獲得生命回復，持續 10 秒。"
      ],
      "buildFrom": [],
      "upgrades": []
    },
    {
      "id": "intermediate-35",
      "name": "巨人腰帶",
      "category": "防禦",
      "categories": [
        "防禦",
        "輔助"
      ],
      "stage": "中階",
      "tier": "中階",
      "order": 134,
      "icon": "../assets/images/items/巨人腰帶.webp",
      "price": 1000,
      "stats": [
        "+300 最大生命"
      ],
      "passives": [],
      "buildFrom": [],
      "upgrades": []
    },
    {
      "id": "intermediate-36",
      "name": "守望者鎧甲",
      "category": "防禦",
      "categories": [
        "防禦",
        "輔助"
      ],
      "stage": "中階",
      "tier": "中階",
      "order": 135,
      "icon": "../assets/images/items/守望者鎧甲.webp",
      "price": 1050,
      "stats": [
        "+35 物理防禦"
      ],
      "passives": [
        "遭受攻擊時降低攻擊者 15% 攻速，持續 1.5 秒。"
      ],
      "buildFrom": [],
      "upgrades": []
    },
    {
      "id": "intermediate-37",
      "name": "鎖子甲",
      "category": "防禦",
      "categories": [
        "防禦"
      ],
      "stage": "中階",
      "tier": "中階",
      "order": 136,
      "icon": "../assets/images/items/鎖子甲.webp",
      "price": 900,
      "stats": [
        "+40 物理防禦"
      ],
      "passives": [],
      "buildFrom": [],
      "upgrades": []
    },
    {
      "id": "intermediate-38",
      "name": "刺藤胸甲",
      "category": "防禦",
      "categories": [
        "防禦"
      ],
      "stage": "中階",
      "tier": "中階",
      "order": 137,
      "icon": "../assets/images/items/刺藤胸甲.webp",
      "price": 1000,
      "stats": [
        "+30 物理防禦"
      ],
      "passives": [
        "遭普攻命中時反彈魔法傷害；敵方英雄傷害附加 40% 重創，持續 3 秒。"
      ],
      "buildFrom": [],
      "upgrades": []
    },
    {
      "id": "intermediate-39",
      "name": "飛翼月甲",
      "category": "防禦",
      "categories": [
        "防禦",
        "輔助"
      ],
      "stage": "中階",
      "tier": "中階",
      "order": 138,
      "icon": "../assets/images/items/飛翼月甲.webp",
      "price": 900,
      "stats": [
        "+150 最大生命",
        "+5% 跑速"
      ],
      "passives": [],
      "buildFrom": [],
      "upgrades": []
    },
    {
      "id": "intermediate-40",
      "name": "負極斗篷",
      "category": "防禦",
      "categories": [
        "防禦",
        "輔助"
      ],
      "stage": "中階",
      "tier": "中階",
      "order": 139,
      "icon": "../assets/images/items/負極斗篷.webp",
      "price": 900,
      "stats": [
        "+40 魔法防禦"
      ],
      "passives": [],
      "buildFrom": [],
      "upgrades": []
    },
    {
      "id": "intermediate-41",
      "name": "冰川護甲",
      "category": "防禦",
      "categories": [
        "防禦",
        "輔助"
      ],
      "stage": "中階",
      "tier": "中階",
      "order": 140,
      "icon": "../assets/images/items/冰川護甲.webp",
      "price": 1000,
      "stats": [
        "+20 物理防禦",
        "+150 最大魔力",
        "+10 技能加速"
      ],
      "passives": [],
      "buildFrom": [],
      "upgrades": []
    },
    {
      "id": "intermediate-42",
      "name": "波濤鱗甲",
      "category": "防禦",
      "categories": [
        "防禦"
      ],
      "stage": "中階",
      "tier": "中階",
      "order": 141,
      "icon": "../assets/images/items/波濤鱗甲.webp",
      "price": 1300,
      "stats": [
        "+40 物理防禦"
      ],
      "passives": [
        "與敵方英雄交戰時，獲得 20% 緩速抗性。"
      ],
      "buildFrom": [],
      "upgrades": []
    }
  ],
  "materials": [
    {
      "id": "dagger",
      "name": "短劍",
      "icon": "../assets/images/items/shoes/dagger.png",
      "stats": [
        "攻擊速度材料"
      ],
      "category": "基本",
      "categories": [
        "基本",
        "鞋子"
      ],
      "stage": "基本",
      "tier": "基本",
      "order": 1,
      "price": 0,
      "passives": [],
      "buildFrom": [],
      "upgrades": []
    },
    {
      "id": "ruby-crystal",
      "name": "紅水晶",
      "icon": "../assets/images/items/shoes/ruby-crystal.png",
      "stats": [
        "生命值材料"
      ],
      "category": "基本",
      "categories": [
        "基本",
        "鞋子"
      ],
      "stage": "基本",
      "tier": "基本",
      "order": 2,
      "price": 0,
      "passives": [],
      "buildFrom": [],
      "upgrades": []
    },
    {
      "id": "amp-tome",
      "name": "增幅典籍",
      "icon": "../assets/images/items/shoes/amp-tome.png",
      "stats": [
        "魔法攻擊材料"
      ],
      "category": "基本",
      "categories": [
        "基本",
        "鞋子"
      ],
      "stage": "基本",
      "tier": "基本",
      "order": 3,
      "price": 0,
      "passives": [],
      "buildFrom": [],
      "upgrades": []
    },
    {
      "id": "mana-ring",
      "name": "魔力戒指",
      "icon": "../assets/images/items/shoes/mana-ring.png",
      "stats": [
        "魔力相關材料"
      ],
      "category": "基本",
      "categories": [
        "基本",
        "鞋子"
      ],
      "stage": "基本",
      "tier": "基本",
      "order": 4,
      "price": 0,
      "passives": [],
      "buildFrom": [],
      "upgrades": []
    },
    {
      "id": "long-sword",
      "name": "長劍",
      "icon": "../assets/images/items/shoes/long-sword.png",
      "stats": [
        "物理攻擊材料"
      ],
      "category": "基本",
      "categories": [
        "基本",
        "鞋子"
      ],
      "stage": "基本",
      "tier": "基本",
      "order": 5,
      "price": 0,
      "passives": [],
      "buildFrom": [],
      "upgrades": []
    }
  ]
}